<?xml version="1.0"?>
<rec type="areas">
 <no/><!-- Land Bridge -->
 <no/><!-- English Channel Coast -->
 <no/><!-- Passable -->
 <v2 x="-530.98041" y="48.199851989746094"/>
 <v2 x="-523.40765" y="62.78864669799805"/>
 <u2>737</u2><!-- Adjoning Passable Areas ID -->
 <rec type="faces">
  <u4_ary>
   43388 <!-- -530.98041 58.21893310546875-->
   42343 <!-- -530.00061 60.00016784667969-->
   46529 <!-- -530.2085 55.00007247924805-->
   43388 <!-- -530.98041 58.21893310546875-->
   43999 <!-- -530.80707 60.00013732910156-->
   42343 <!-- -530.00061 60.00016784667969-->
   42343 <!-- -530.00061 60.00016784667969-->
   46812 <!-- -530.00079 55.00007247924805-->
   46529 <!-- -530.2085 55.00007247924805-->
   46529 <!-- -530.2085 55.00007247924805-->
   46812 <!-- -530.00079 55.00007247924805-->
   51824 <!-- -530.00073 54.42152404785156-->
   51824 <!-- -530.00073 54.42152404785156-->
   46812 <!-- -530.00079 55.00007247924805-->
   51861 <!-- -525.00043 55.00007247924805-->
   48621 <!-- -529.23169 52.27952194213867-->
   51824 <!-- -530.00073 54.42152404785156-->
   51861 <!-- -525.00043 55.00007247924805-->
   48621 <!-- -529.23169 52.27952194213867-->
   43469 <!-- -524.90344 52.23534-->
   39462 <!-- -524.93134 51.752262115478516-->
   48621 <!-- -529.23169 52.27952194213867-->
   47223 <!-- -524.77338 52.61622619628906-->
   43469 <!-- -524.90344 52.23534-->
   48621 <!-- -529.23169 52.27952194213867-->
   51861 <!-- -525.00043 55.00007247924805-->
   47223 <!-- -524.77338 52.61622619628906-->
   51861 <!-- -525.00043 55.00007247924805-->
   51068 <!-- -524.47614 52.93208312988281-->
   47223 <!-- -524.77338 52.61622619628906-->
   51861 <!-- -525.00043 55.00007247924805-->
   51220 <!-- -524.28107 53.164337158203125-->
   51068 <!-- -524.47614 52.93208312988281-->
   48621 <!-- -529.23169 52.27952194213867-->
   17639 <!-- -525.38654 51.25062561035156-->
   4307 <!-- -528.20764 49.99998474121094-->
   48621 <!-- -529.23169 52.27952194213867-->
   21510 <!-- -525.00043 51.60365295410156-->
   17639 <!-- -525.38654 51.25062561035156-->
   48621 <!-- -529.23169 52.27952194213867-->
   39462 <!-- -524.93134 51.752262115478516-->
   21510 <!-- -525.00043 51.60365295410156-->
   13067 <!-- -525.69312 50.55387-->
   7044 <!-- -525.81372 49.99998474121094-->
   4307 <!-- -528.20764 49.99998474121094-->
   14857 <!-- -525.63739 50.96262741088867-->
   13067 <!-- -525.69312 50.55387-->
   4307 <!-- -528.20764 49.99998474121094-->
   17639 <!-- -525.38654 51.25062561035156-->
   14857 <!-- -525.63739 50.96262741088867-->
   4307 <!-- -528.20764 49.99998474121094-->
   51861 <!-- -525.00043 55.00007247924805-->
   56418 <!-- -524.25317 53.582374572753906-->
   51220 <!-- -524.28107 53.164337158203125-->
   51861 <!-- -525.00043 55.00007247924805-->
   45324 <!-- -524.22528 54.19550704956055-->
   56418 <!-- -524.25317 53.582374572753906-->
   51861 <!-- -525.00043 55.00007247924805-->
   47429 <!-- -524.11383 54.5949821472168-->
   45324 <!-- -524.22528 54.19550704956055-->
   51861 <!-- -525.00043 55.00007247924805-->
   53993 <!-- -523.90015 54.81791687011719-->
   47429 <!-- -524.11383 54.5949821472168-->
   51861 <!-- -525.00043 55.00007247924805-->
   53166 <!-- -523.7887 55.0001220703125-->
   53993 <!-- -523.90015 54.81791687011719-->
   42343 <!-- -530.00061 60.00016784667969-->
   43999 <!-- -530.80707 60.00013732910156-->
   55965 <!-- -530.68109 60.53483581542969-->
   55965 <!-- -530.68109 60.53483581542969-->
   22910 <!-- -530.00055 61.54313-->
   42343 <!-- -530.00061 60.00016784667969-->
   42343 <!-- -530.00061 60.00016784667969-->
   22910 <!-- -530.00055 61.54313-->
   25094 <!-- -526.22266 62.63017272949219-->
   22910 <!-- -530.00055 61.54313-->
   19786 <!-- -528.69604 62.29932-->
   25094 <!-- -526.22266 62.63017272949219-->
   47227 <!-- -525.00043 59.99997-->
   42343 <!-- -530.00061 60.00016784667969-->
   25094 <!-- -526.22266 62.63017272949219-->
   27566 <!-- -525.00055 62.71796417236328-->
   47227 <!-- -525.00043 59.99997-->
   25094 <!-- -526.22266 62.63017272949219-->
   27671 <!-- -524.79205 62.732933044433594-->
   47227 <!-- -525.00043 59.99997-->
   27566 <!-- -525.00055 62.71796417236328-->
   27671 <!-- -524.79205 62.732933044433594-->
   56706 <!-- -524.55054 60.93069-->
   47227 <!-- -525.00043 59.99997-->
   27671 <!-- -524.79205 62.732933044433594-->
   26184 <!-- -524.46698 62.47279357910156-->
   56706 <!-- -524.55054 60.93069-->
   56706 <!-- -524.55054 60.93069-->
   51873 <!-- -524.50409 60.52192687988281-->
   47227 <!-- -525.00043 59.99997-->
   26184 <!-- -524.46698 62.47279357910156-->
   59252 <!-- -524.40192 61.2837-->
   56706 <!-- -524.55054 60.93069-->
   26184 <!-- -524.46698 62.47279357910156-->
   23122 <!-- -524.19757 62.14766311645508-->
   59252 <!-- -524.40192 61.2837-->
   23122 <!-- -524.19757 62.14766311645508-->
   18198 <!-- -524.17896 61.757484436035156-->
   59252 <!-- -524.40192 61.2837-->
   51873 <!-- -524.50409 60.52192687988281-->
   48044 <!-- -524.30896 59.999996185302734-->
   47227 <!-- -525.00043 59.99997-->
   29087 <!-- -524.29022 62.78864669799805-->
   26184 <!-- -524.46698 62.47279357910156-->
   27671 <!-- -524.79205 62.732933044433594-->
   29087 <!-- -524.29022 62.78864669799805-->
   23122 <!-- -524.19757 62.14766311645508-->
   26184 <!-- -524.46698 62.47279357910156-->
   29087 <!-- -524.29022 62.78864669799805-->
   24788 <!-- -524.01154 62.53782-->
   23122 <!-- -524.19757 62.14766311645508-->
   17751 <!-- -523.86292 62.119773864746094-->
   18198 <!-- -524.17896 61.757484436035156-->
   23122 <!-- -524.19757 62.14766311645508-->
   24788 <!-- -524.01154 62.53782-->
   17751 <!-- -523.86292 62.119773864746094-->
   23122 <!-- -524.19757 62.14766311645508-->
   21876 <!-- -523.82574 61.66457-->
   55483 <!-- -523.90002 61.40445327758789-->
   18198 <!-- -524.17896 61.757484436035156-->
   17751 <!-- -523.86292 62.119773864746094-->
   21876 <!-- -523.82574 61.66457-->
   18198 <!-- -524.17896 61.757484436035156-->
   56286 <!-- -524.18805 60.9028-->
   51873 <!-- -524.50409 60.52192687988281-->
   56706 <!-- -524.55054 60.93069-->
   56286 <!-- -524.18805 60.9028-->
   56706 <!-- -524.55054 60.93069-->
   59252 <!-- -524.40192 61.2837-->
   46347 <!-- -523.8443 60.00001525878906-->
   48044 <!-- -524.30896 59.999996185302734-->
   51873 <!-- -524.50409 60.52192687988281-->
   56286 <!-- -524.18805 60.9028-->
   46347 <!-- -523.8443 60.00001525878906-->
   51873 <!-- -524.50409 60.52192687988281-->
   59211 <!-- -524.08588 61.15362548828125-->
   56286 <!-- -524.18805 60.9028-->
   59252 <!-- -524.40192 61.2837-->
   59211 <!-- -524.08588 61.15362548828125-->
   59252 <!-- -524.40192 61.2837-->
   18198 <!-- -524.17896 61.757484436035156-->
   55483 <!-- -523.90002 61.40445327758789-->
   59211 <!-- -524.08588 61.15362548828125-->
   18198 <!-- -524.17896 61.757484436035156-->
   36304 <!-- -523.67706 58.07867431640625-->
   30764 <!-- -524.30896 57.632774353027344-->
   33315 <!-- -524.021 58.31093215942383-->
   41616 <!-- -523.52838 58.61749-->
   36304 <!-- -523.67706 58.07867431640625-->
   33315 <!-- -524.021 58.31093215942383-->
   43067 <!-- -523.50983 59.06340408325195-->
   41616 <!-- -523.52838 58.61749-->
   33315 <!-- -524.021 58.31093215942383-->
   42320 <!-- -523.95599 59.239925384521484-->
   48044 <!-- -524.30896 59.999996185302734-->
   46347 <!-- -523.8443 60.00001525878906-->
   40880 <!-- -523.8631 58.886905670166016-->
   43067 <!-- -523.50983 59.06340408325195-->
   33315 <!-- -524.021 58.31093215942383-->
   40880 <!-- -523.8631 58.886905670166016-->
   42320 <!-- -523.95599 59.239925384521484-->
   43067 <!-- -523.50983 59.06340408325195-->
   42320 <!-- -523.95599 59.239925384521484-->
   46347 <!-- -523.8443 60.00001525878906-->
   43067 <!-- -523.50983 59.06340408325195-->
   47227 <!-- -525.00043 59.99997-->
   51861 <!-- -525.00043 55.00007247924805-->
   46812 <!-- -530.00079 55.00007247924805-->
   46812 <!-- -530.00079 55.00007247924805-->
   42343 <!-- -530.00061 60.00016784667969-->
   47227 <!-- -525.00043 59.99997-->
   23872 <!-- -524.3833 56.871002197265625-->
   3796 <!-- -524.21606 56.28573226928711-->
   51861 <!-- -525.00043 55.00007247924805-->
   3796 <!-- -524.21606 56.28573226928711-->
   57491 <!-- -523.90021 55.82124328613281-->
   51861 <!-- -525.00043 55.00007247924805-->
   57491 <!-- -523.90021 55.82124328613281-->
   50997 <!-- -523.79803 55.32888-->
   51861 <!-- -525.00043 55.00007247924805-->
   50997 <!-- -523.79803 55.32888-->
   53166 <!-- -523.7887 55.0001220703125-->
   51861 <!-- -525.00043 55.00007247924805-->
   47227 <!-- -525.00043 59.99997-->
   40880 <!-- -523.8631 58.886905670166016-->
   33315 <!-- -524.021 58.31093215942383-->
   47227 <!-- -525.00043 59.99997-->
   48044 <!-- -524.30896 59.999996185302734-->
   42320 <!-- -523.95599 59.239925384521484-->
   47227 <!-- -525.00043 59.99997-->
   42320 <!-- -523.95599 59.239925384521484-->
   40880 <!-- -523.8631 58.886905670166016-->
   30764 <!-- -524.30896 57.632774353027344-->
   23872 <!-- -524.3833 56.871002197265625-->
   51861 <!-- -525.00043 55.00007247924805-->
   30764 <!-- -524.30896 57.632774353027344-->
   51861 <!-- -525.00043 55.00007247924805-->
   47227 <!-- -525.00043 59.99997-->
   30764 <!-- -524.30896 57.632774353027344-->
   47227 <!-- -525.00043 59.99997-->
   33315 <!-- -524.021 58.31093215942383-->
   32195 <!-- -523.93719 57.326194763183594-->
   24941 <!-- -523.96503 56.79667-->
   23872 <!-- -524.3833 56.871002197265625-->
   32195 <!-- -523.93719 57.326194763183594-->
   23872 <!-- -524.3833 56.871002197265625-->
   30764 <!-- -524.30896 57.632774353027344-->
   36304 <!-- -523.67706 58.07867431640625-->
   32195 <!-- -523.93719 57.326194763183594-->
   30764 <!-- -524.30896 57.632774353027344-->
   2893 <!-- -523.82568 56.36933517456055-->
   3796 <!-- -524.21606 56.28573226928711-->
   23872 <!-- -524.3833 56.871002197265625-->
   24941 <!-- -523.96503 56.79667-->
   2893 <!-- -523.82568 56.36933517456055-->
   23872 <!-- -524.3833 56.871002197265625-->
   2893 <!-- -523.82568 56.36933517456055-->
   57491 <!-- -523.90021 55.82124328613281-->
   3796 <!-- -524.21606 56.28573226928711-->
   2893 <!-- -523.82568 56.36933517456055-->
   4580 <!-- -523.53772 55.979164123535156-->
   57491 <!-- -523.90021 55.82124328613281-->
   4580 <!-- -523.53772 55.979164123535156-->
   59106 <!-- -523.41693 55.523956298828125-->
   57491 <!-- -523.90021 55.82124328613281-->
   59106 <!-- -523.41693 55.523956298828125-->
   50997 <!-- -523.79803 55.32888-->
   57491 <!-- -523.90021 55.82124328613281-->
   59106 <!-- -523.41693 55.523956298828125-->
   52958 <!-- -523.40765 55.0001335144043-->
   50997 <!-- -523.79803 55.32888-->
   52958 <!-- -523.40765 55.0001335144043-->
   53166 <!-- -523.7887 55.0001220703125-->
   50997 <!-- -523.79803 55.32888-->
   47223 <!-- -524.77338 52.61622619628906-->
   44139 <!-- -524.3924 52.383975982666016-->
   42018 <!-- -524.53174 52.08669-->
   47223 <!-- -524.77338 52.61622619628906-->
   51068 <!-- -524.47614 52.93208312988281-->
   44139 <!-- -524.3924 52.383975982666016-->
   51068 <!-- -524.47614 52.93208312988281-->
   51220 <!-- -524.28107 53.164337158203125-->
   44139 <!-- -524.3924 52.383975982666016-->
   51220 <!-- -524.28107 53.164337158203125-->
   46424 <!-- -524.05798 52.718406677246094-->
   44139 <!-- -524.3924 52.383975982666016-->
   51220 <!-- -524.28107 53.164337158203125-->
   53406 <!-- -523.91864 53.20148-->
   46424 <!-- -524.05798 52.718406677246094-->
   51220 <!-- -524.28107 53.164337158203125-->
   56418 <!-- -524.25317 53.582374572753906-->
   53406 <!-- -523.91864 53.20148-->
   56418 <!-- -524.25317 53.582374572753906-->
   49113 <!-- -523.85358 54.27911-->
   53406 <!-- -523.91864 53.20148-->
   56418 <!-- -524.25317 53.582374572753906-->
   45324 <!-- -524.22528 54.19550704956055-->
   49113 <!-- -523.85358 54.27911-->
   45324 <!-- -524.22528 54.19550704956055-->
   47429 <!-- -524.11383 54.5949821472168-->
   49113 <!-- -523.85358 54.27911-->
   47429 <!-- -524.11383 54.5949821472168-->
   53993 <!-- -523.90015 54.81791687011719-->
   49113 <!-- -523.85358 54.27911-->
   53993 <!-- -523.90015 54.81791687011719-->
   44467 <!-- -523.48199 54.6971549987793-->
   49113 <!-- -523.85358 54.27911-->
   53993 <!-- -523.90015 54.81791687011719-->
   52958 <!-- -523.40765 55.0001335144043-->
   44467 <!-- -523.48199 54.6971549987793-->
   53993 <!-- -523.90015 54.81791687011719-->
   53166 <!-- -523.7887 55.0001220703125-->
   52958 <!-- -523.40765 55.0001335144043-->
   4307 <!-- -528.20764 49.99998474121094-->
   11040 <!-- -526.78918 48.81667-->
   13444 <!-- -527.13397 48.52113-->
   4307 <!-- -528.20764 49.99998474121094-->
   4811 <!-- -526.10175 49.55055618286133-->
   11040 <!-- -526.78918 48.81667-->
   4307 <!-- -528.20764 49.99998474121094-->
   7044 <!-- -525.81372 49.99998474121094-->
   4811 <!-- -526.10175 49.55055618286133-->
   13444 <!-- -527.13397 48.52113-->
   11040 <!-- -526.78918 48.81667-->
   16252 <!-- -526.90076 48.199851989746094-->
   11040 <!-- -526.78918 48.81667-->
   13303 <!-- -526.44543 48.60297775268555-->
   16252 <!-- -526.90076 48.199851989746094-->
   11040 <!-- -526.78918 48.81667-->
   4811 <!-- -526.10175 49.55055618286133-->
   13303 <!-- -526.44543 48.60297775268555-->
   4811 <!-- -526.10175 49.55055618286133-->
   722 <!-- -525.63721 49.45765686035156-->
   13303 <!-- -526.44543 48.60297775268555-->
   4811 <!-- -526.10175 49.55055618286133-->
   7044 <!-- -525.81372 49.99998474121094-->
   722 <!-- -525.63721 49.45765686035156-->
   7044 <!-- -525.81372 49.99998474121094-->
   6495 <!-- -525.39563 49.99998474121094-->
   722 <!-- -525.63721 49.45765686035156-->
   6495 <!-- -525.39563 49.99998474121094-->
   7044 <!-- -525.81372 49.99998474121094-->
   13067 <!-- -525.69312 50.55387-->
   6495 <!-- -525.39563 49.99998474121094-->
   13067 <!-- -525.69312 50.55387-->
   14857 <!-- -525.63739 50.96262741088867-->
   14529 <!-- -525.17273 50.86971664428711-->
   6495 <!-- -525.39563 49.99998474121094-->
   14857 <!-- -525.63739 50.96262741088867-->
   16397 <!-- -525.00043 51.01835250854492-->
   14529 <!-- -525.17273 50.86971664428711-->
   14857 <!-- -525.63739 50.96262741088867-->
   16397 <!-- -525.00043 51.01835250854492-->
   14857 <!-- -525.63739 50.96262741088867-->
   17639 <!-- -525.38654 51.25062561035156-->
   21510 <!-- -525.00043 51.60365295410156-->
   16397 <!-- -525.00043 51.01835250854492-->
   17639 <!-- -525.38654 51.25062561035156-->
   21510 <!-- -525.00043 51.60365295410156-->
   18366 <!-- -524.67108 51.29706-->
   16397 <!-- -525.00043 51.01835250854492-->
   21510 <!-- -525.00043 51.60365295410156-->
   39462 <!-- -524.93134 51.752262115478516-->
   18366 <!-- -524.67108 51.29706-->
   39462 <!-- -524.93134 51.752262115478516-->
   21124 <!-- -524.55963 51.6222-->
   18366 <!-- -524.67108 51.29706-->
   39462 <!-- -524.93134 51.752262115478516-->
   42018 <!-- -524.53174 52.08669-->
   21124 <!-- -524.55963 51.6222-->
   39462 <!-- -524.93134 51.752262115478516-->
   43469 <!-- -524.90344 52.23534-->
   42018 <!-- -524.53174 52.08669-->
   43469 <!-- -524.90344 52.23534-->
   47223 <!-- -524.77338 52.61622619628906-->
   42018 <!-- -524.53174 52.08669-->
  </u4_ary>
 </rec>
 <ary type="outlines">
  <rec type="outlines">
   <yes/>
   <v2 x="-530.98041" y="48.199851989746094"/>
   <v2 x="-523.40765" y="62.78864669799805"/>
   <u4_ary>
    16252 <!-- -526.90076 48.199851989746094-->
    13303 <!-- -526.44543 48.60297775268555-->
    722 <!-- -525.63721 49.45765686035156-->
    6495 <!-- -525.39563 49.99998474121094-->
    14529 <!-- -525.17273 50.86971664428711-->
    16397 <!-- -525.00043 51.01835250854492-->
    18366 <!-- -524.67108 51.29706-->
    21124 <!-- -524.55963 51.6222-->
    42018 <!-- -524.53174 52.08669-->
    44139 <!-- -524.3924 52.383975982666016-->
    46424 <!-- -524.05798 52.718406677246094-->
    53406 <!-- -523.91864 53.20148-->
    49113 <!-- -523.85358 54.27911-->
    44467 <!-- -523.48199 54.6971549987793-->
    52958 <!-- -523.40765 55.0001335144043-->
    59106 <!-- -523.41693 55.523956298828125-->
    4580 <!-- -523.53772 55.979164123535156-->
    2893 <!-- -523.82568 56.36933517456055-->
    24941 <!-- -523.96503 56.79667-->
    32195 <!-- -523.93719 57.326194763183594-->
    36304 <!-- -523.67706 58.07867431640625-->
    41616 <!-- -523.52838 58.61749-->
    43067 <!-- -523.50983 59.06340408325195-->
    46347 <!-- -523.8443 60.00001525878906-->
    56286 <!-- -524.18805 60.9028-->
    59211 <!-- -524.08588 61.15362548828125-->
    55483 <!-- -523.90002 61.40445327758789-->
    21876 <!-- -523.82574 61.66457-->
    17751 <!-- -523.86292 62.119773864746094-->
    24788 <!-- -524.01154 62.53782-->
    29087 <!-- -524.29022 62.78864669799805-->
    27671 <!-- -524.79205 62.732933044433594-->
    27566 <!-- -525.00055 62.71796417236328-->
    25094 <!-- -526.22266 62.63017272949219-->
    19786 <!-- -528.69604 62.29932-->
    22910 <!-- -530.00055 61.54313-->
    55965 <!-- -530.68109 60.53483581542969-->
    43999 <!-- -530.80707 60.00013732910156-->
    43388 <!-- -530.98041 58.21893310546875-->
    46529 <!-- -530.2085 55.00007247924805-->
    51824 <!-- -530.00073 54.42152404785156-->
    48621 <!-- -529.23169 52.27952194213867-->
    4307 <!-- -528.20764 49.99998474121094-->
    13444 <!-- -527.13397 48.52113-->
   </u4_ary>
   <ary type="connectivity">
    <connectivity region="156 (new_grenada)" area="0" from="0" to="29"/>
    <connectivity region="36 (all)" area="26" from="30" to="30"/>
    <connectivity region="156 (new_grenada)" area="0" from="31" to="42"/>
    <connectivity region="36 (all)" area="27" from="43" to="43"/>
   </ary>
  </rec>
 </ary>
 <u2>248</u2><!-- Impassable Land Areas ID (65535=Passable) -->
 <u2>104</u2><!-- Island ID (65535=Navigable, 104=ETW Mainland) -->
</rec>
