<?xml version="1.0"?>
<rec type="CAI_WORLD_RESOURCE_MOBILES">
 <owned_direct>1292</owned_direct><!-- Faction AI ID -->
 <cai_situated x="125.56494903564453" y="421.70587158203125" region_id="854" theatre_id="34" area_id="13"/>
 <rec type="CAI_BDI_COMPONENT_PROPERTY_SET">
  <u>0</u>
 </rec>
 <u>5929</u><!-- Character Resource AI ID -->
 <flt>100.0</flt>
 <flt>100.0</flt>
 <flt>0.0</flt>
 <flt>100.0</flt>
 <u>1</u>
 <no/>
 <u4_ary/>
 <u4_ary>8502 0 9338 8 9461 0 9364 9 9365 5 9366 5 9371 5 9375 5 9405 7 9444 12 9445 5 9446 6 9460 7 9464 14 9471 13 9473 14 9483 11 9487 6 9488 5 9493 13 9496 13 9506 18 9507 18 9508 15 9538 15 9539 16 9540 13 9543 7 9545 4 9546 5 9547 5 9552 10 9553 11 9554 11 12130 2 12132 0 13718 0 16119 0 16849 0 18302 0 19330 0 21893 0 22464 0 24749 0 24959 0 26007 0 27108 0 27243 0 27572 0 28856 0 28965 0 29928 0 31104 0 32597 0 33773 0 34338 0 34345 0 34780 0 34918 0 34920 0 34921 1 34782 5 36160 0 36278 0 36279 1 34773 5 41477 0 41690 0 42776 0 43503 0 46132 0 46342 0 47612 0 48383 0 51814 0 52026 0 53143 0 53356 0 54471 0 55511 0 57125 0 57335 0 59025 0 59224 0 60963 0 61709 0 62723 0 63476 0 65491 0 65705 0 66861 0 67075 0 68174 0 68380 0 69478 0 69692 0 70770 0 70979 0 71279 0 72278 0 74887 0 75101 0 77722 0 78500 0 79520 0</u4_ary><!-- BDI Information -->
 <u>0</u>
 <u>105</u><!-- HLCIS ID -->
 <u4_ary/>
 <u4_ary>8502 10 9338 16 9461 9364 9365 9366 9371 9375 9405 9444 9445 9446 9460 9464 9471 9473 9483 9487 9488 9493 9496 9506 9507 9508 9538 9539 9540 9543 9545 9546 9547 9552 9553 9554 12130 20 12132 7863 13718 7855 16119 14784 16849 14776 18302 17717 19330 17709 21893 19739 22464 19731 24749 22843 24959 22835 26007 25847 27108 25839 27243 25858 27572 27374 28856 27366 28965 27385 29928 29195 31104 29187 32597 32086 33773 32078 34338 34218 34345 34226 34780 34237 34918 34919 34262 34782 34920 34921 36160 34256 36278 36279 34773 41477 40558 41690 40550 42776 41866 43503 41858 46132 45216 46342 45208 47612 46905 48383 46897 51814 50894 52026 50886 53143 52217 53356 52209 54471 54271 55511 54263 57125 56131 57335 56123 59025 58109 59224 58101 60963 60162 61709 60154 62723 61951 63476 61943 65491 64593 65705 64585 66861 65922 67075 65914 68174 67261 68380 67253 69478 68550 69692 68542 70770 69866 70979 69858 71279 71144 72278 71136 74887 73965 75101 73957 77722 76919 78500 76911 79520 78766</u4_ary><!-- BDI Information -->
 <ary type="CAI_BDI_COMPONENT_BLOCK_OWNS">
  <rec type="CAI_BDI_COMPONENT_BLOCK_OWNS">
   <u>34921</u><!-- BDI Information -->
   <u>5929</u><!-- Character Resource AI ID -->
   <flt>0.0</flt>
   <flt>0.0</flt>
   <u>0</u>
  </rec>
  <rec type="CAI_BDI_COMPONENT_BLOCK_OWNS">
   <u>36279</u><!-- BDI Information -->
   <u>5929</u><!-- Character Resource AI ID -->
   <flt>0.0</flt>
   <flt>0.0</flt>
   <u>0</u>
  </rec>
 </ary>
 <u>2</u>
 <u>0</u>
 <u4_ary>34921 36279</u4_ary><!-- BDI Information -->
 <u4_ary/>
 <u4_ary/>
 <u4_ary>8502 9338 9364 9365 9366 9371 9375 9405 9444 9445 9446 9459 9460 9461 9464 9471 9473 9483 9487 9488 9493 9496 9506 9507 9508 9538 9539 9540 9543 9545 9546 9547 9552 9553 9554 13393 13396 13685 13687 13690 13718 13720 13721 13723 13724 13726 13728 13729 13730 13731 13733 13752 13753 13754 13755 13794 13795 13796 13829 13834 16649 16652 16830 16832 16835 16849 16851 16852 16854 16855 16857 16859 16860 16861 16862 16864 16870 16871 16872 16873 16888 16889 16890 16901 16906 18301 18306 18337 18339 18342 19330 19332 19333 19335 19336 19338 19340 19341 19342 19343 19345 19351 19352 19353 19354 19370 19371 19372 19383 19388 22308 22311 22445 22447 22450 22464 22466 22467 22469 22470 22472 22474 22475 22476 22477 22479 22485 22486 22487 22488 22503 22504 22505 22516 22521 24748 24753 24940 24942 24945 24959 24961 24962 24964 24965 24967 24969 24970 24971 24972 24974 24980 24981 24982 24983 24999 25000 25001 25012 25017 26006 26022 26035 26047 26054 26057 26059 27089 27091 27094 27108 27109 27110 27112 27113 27115 27117 27118 27119 27120 27122 27140 27141 27142 27153 27158 27243 27564 27585 27589 27614 28736 28740 28856 28857 28858 28860 28861 28863 28865 28866 28867 28868 28870 28876 28877 28878 28879 28885 28886 28887 28891 28896 28965 30969 30972 31085 31087 31090 31104 31106 31107 31109 31110 31112 31114 31115 31116 31117 31119 31125 31126 31127 31128 31143 31144 31145 31156 31161 33620 33623 33754 33756 33759 33773 33775 33776 33778 33779 33781 33783 33784 33785 33786 33788 33794 33795 33796 33797 33812 33813 33814 33825 33830 34366 34391 34438 34338 34368 34387 34389 34393 34400 34401 34352 34358 34365 34390 34433 34440 34780 34776 34920 35808 35811 35973 35975 35978 35984 35985 35986 35987 36002 36003 36004 36160 36278 41476 41481 41671 41673 41676 41690 41692 41693 41695 41696 41698 41700 41701 41702 41703 41705 41711 41712 41713 41714 41730 41731 41732 41743 41748 43303 43306 43484 43486 43489 43503 43505 43506 43508 43509 43511 43513 43514 43515 43516 43518 43524 43525 43526 43527 43542 43543 43544 43555 43560 46131 46136 46323 46325 46328 46342 46344 46345 46347 46348 46350 46352 46353 46354 46355 46357 46363 46364 46365 46366 46382 46383 46384 46395 46400 48183 48186 48364 48366 48369 48383 48385 48386 48388 48389 48391 48393 48394 48395 48396 48398 48404 48405 48406 48407 48422 48423 48424 48435 48440 51813 51818 52007 52009 52012 52026 52028 52029 52031 52032 52034 52036 52037 52038 52039 52041 52047 52048 52049 52050 52066 52067 52068 52079 52084 53142 53147 53337 53339 53342 53356 53358 53359 53361 53362 53364 53366 53367 53368 53369 53371 53377 53378 53379 53380 53396 53397 53398 53409 53414 55325 55328 55503 55505 55508 55511 55513 55514 55516 55517 55519 55521 55522 55523 55524 55526 55532 55533 55534 55535 55551 55552 55553 55564 55569 57124 57129 57316 57318 57321 57335 57337 57338 57340 57341 57343 57345 57346 57347 57348 57350 57356 57357 57358 57359 57375 57376 57377 57388 57393 59024 59029 59205 59207 59210 59224 59226 59227 59229 59230 59232 59234 59235 59236 59237 59239 59245 59246 59247 59248 59264 59265 59266 59277 59282 61509 61512 61690 61692 61695 61709 61711 61712 61714 61715 61717 61719 61720 61721 61722 61724 61730 61731 61732 61733 61748 61749 61750 61761 61766 63276 63279 63457 63459 63462 63476 63478 63479 63481 63482 63484 63486 63487 63488 63489 63491 63497 63498 63499 63500 63515 63516 63517 63528 63533 65490 65495 65686 65688 65691 65705 65707 65708 65710 65711 65713 65715 65716 65717 65718 65720 65726 65727 65728 65729 65745 65746 65747 65758 65763 66860 66865 67056 67058 67061 67075 67077 67078 67080 67081 67083 67085 67086 67087 67088 67090 67096 67097 67098 67099 67115 67116 67117 67128 67133 68173 68178 68361 68363 68366 68380 68382 68383 68385 68386 68388 68390 68391 68392 68393 68395 68401 68402 68403 68404 68420 68421 68422 68433 68438 69477 69482 69673 69675 69678 69692 69694 69695 69697 69698 69700 69702 69703 69704 69705 69707 69713 69714 69715 69716 69732 69733 69734 69745 69750 70769 70774 70960 70962 70965 70979 70981 70982 70984 70985 70987 70989 70990 70991 70992 70994 71000 71001 71002 71003 71019 71020 71021 71032 71037 71278 71280 71282 72072 72076 72259 72261 72264 72278 72279 72280 72282 72283 72285 72287 72288 72289 72290 72292 72298 72299 72300 72301 72321 72326 74886 74891 75082 75084 75087 75101 75103 75104 75106 75107 75109 75111 75112 75113 75114 75116 75122 75123 75124 75125 75141 75142 75143 75154 75159 78300 78303 78481 78483 78486 78500 78502 78503 78505 78506 78508 78510 78511 78512 78513 78515 78521 78522 78523 78524 78539 78540 78541 78552 78557</u4_ary><!-- BDI Information -->
 <no/>
 <u>0</u>
 <no/>
 <rec type="CAI_RESOURCE_MOBILE">
  <u>5928</u><!-- Character AI ID -->
  <u>2570</u><!-- Settlement AI ID -->
  <u>0</u><!-- Settlement Character AI ID -->
  <ary type="CAI_RESOURCE_MOBILE_SIEGE_INFORMATION"/>
  <u4_ary>5928</u4_ary><!-- Character AI IDs -->
  <u4_ary>5930 5931 5932</u4_ary><!-- Character Unit AI IDs -->
  <yes/>
  <no/>
  <no/>
  <u>0</u>
  <u>581001120</u><!-- Army ID -->
  <u4_ary/>
  <u>0</u>
  <u>0</u>
  <u4_ary/>
  <u>0</u>
 </rec>
</rec>
