<?xml version="1.0"?>
<rec type="slot_descriptions">
 <s>port:croatia:zadar</s>
 <s>port</s>
 <v2 x="106.49748" y="316.50494"/>
 <v2 x="105.25786590576172" y="315.66034"/>
 <angle>55.734</angle>
 <no/>
 <v2_ary><!-- Land Area -->
  107.53596,316.66794
  107.40427,315.97321
  106.66048,315.46646
  105.5907,317.03668
  106.33449,317.54343
  107.02922,317.41171
 </v2_ary>
 <v2_ary><!-- Sea Area (present only for ports) -->
  106.57783508300781,315.41016
  105.83404541015625,314.90341
  105.13931,315.03513
  104.63257598876953,315.7789
  104.76427459716797,316.47363
  105.50806,316.98038
 </v2_ary>
 <v2_ary><!-- Total Area (different from land area only in ports) -->
  105.83404541015625,314.90341
  105.13931,315.03513
  104.63257598876953,315.7789
  104.76427459716797,316.47363
  107.16092,318.10648
  107.85565,317.97476
  108.36239,317.23099
  108.23069,316.53625
 </v2_ary>
</rec>
