<?xml version="1.0"?>
<rec type="slot_descriptions">
 <s>settlement:sweden:stockholm:settlement_road</s>
 <s>settlement_road</s>
 <v2 x="125.60334" y="420.37546"/>
 <v2 x="125.60334" y="420.37546"/>
 <angle>315.0</angle>
 <yes/>
 <v2_ary><!-- Land Area -->
  125.24979,421.36542
  125.95689392089844,421.36542
  126.59329,420.729
  126.59329,420.02191
  125.95689392089844,419.3855
  125.24979,419.3855
  124.61339,420.02191
  124.61339,420.729
 </v2_ary>
 <v2_ary/><!-- Sea Area (present only for ports) -->
 <v2_ary><!-- Total Area (different from land area only in ports) -->
  125.24979,421.36542
  125.95689392089844,421.36542
  126.59329,420.729
  126.59329,420.02191
  125.95689392089844,419.3855
  125.24979,419.3855
  124.61339,420.02191
  124.61339,420.729
 </v2_ary>
</rec>
