<?xml version="1.0"?>
<rec type="slot_descriptions">
 <s>wheat:ingria:central</s>
 <s>wheat</s>
 <v2 x="220.3895" y="422.17181"/>
 <v2 x="220.3895" y="422.17181"/>
 <angle>315.0</angle>
 <no/>
 <v2_ary><!-- Land Area -->
  220.03595,423.16177
  220.74304,423.16177
  221.37944,422.52536
  221.37944,421.81827
  220.74304,421.18185
  220.03595,421.18185
  219.39955,421.81827
  219.39955,422.52536
 </v2_ary>
 <v2_ary/><!-- Sea Area (present only for ports) -->
 <v2_ary><!-- Total Area (different from land area only in ports) -->
  220.03595,423.16177
  220.74304,423.16177
  221.37944,422.52536
  221.37944,421.81827
  220.74304,421.18185
  220.03595,421.18185
  219.39955,421.81827
  219.39955,422.52536
 </v2_ary>
</rec>
