<?xml version="1.0"?>
<rec type="areas">
 <no/><!-- Land Bridge -->
 <no/><!-- English Channel Coast -->
 <no/><!-- Passable -->
 <v2 x="-667.00818" y="113.63028"/>
 <v2 x="-634.31372" y="126.51695"/>
 <u2>65535</u2><!-- Adjoning Passable Areas ID -->
 <ary type="outlines">
  <rec type="outlines">
   <yes/>
   <v2 x="-667.00818" y="113.63028"/>
   <v2 x="-634.31372" y="126.51695"/>
   <u4_ary>
    12450 <!-- -636.64014 115.02079-->
    17020 <!-- -635.00891 115.77272-->
    28963 <!-- -634.31372 118.8669-->
    34575 <!-- -634.67303 120.00008392333984-->
    35076 <!-- -634.91583 121.29196-->
    1227 <!-- -636.81799 123.34405-->
    49576 <!-- -640.01251 124.99998-->
    15901 <!-- -643.0285 126.45533-->
    14090 <!-- -645.00061 126.51695-->
    15362 <!-- -648.34058 125.92416381835938-->
    46703 <!-- -650.00055 125.74942-->
    12897 <!-- -655.00073 125.00019-->
    14772 <!-- -660.00061 123.64757537841797-->
    14282 <!-- -663.82098 123.11642456054688-->
    23984 <!-- -665.00061 122.5087661743164-->
    28164 <!-- -666.3252 121.82637-->
    36115 <!-- -667.00818 119.99989-->
    43894 <!-- -666.40106 118.33568572998047-->
    5998 <!-- -665.00055 117.12150573730469-->
    11882 <!-- -661.99982 116.81797-->
    3181 <!-- -660.00037 117.12898-->
    10181 <!-- -655.00049 117.95625-->
    7931 <!-- -650.00055 117.07828-->
    20898 <!-- -647.50574 116.43857-->
    7172 <!-- -645.00061 115.0002-->
    9415 <!-- -640.08923 113.63028-->
    5956 <!-- -638.71503 113.78258-->
   </u4_ary>
   <ary type="connectivity">
    <connectivity region="5 (light_forest)" area="10" from="0" to="13"/>
    <connectivity region="6 (hilly_light_forest)" area="5" from="14" to="26"/>
   </ary>
  </rec>
 </ary>
 <u2>65535</u2>
 <u2>65535</u2><!-- Impassable Land Areas ID (65535=Passable) -->
</rec>
