<?xml version="1.0"?>
<rec type="TRADE_SEGMENTS">
 <ary type="COMMERCE_RAIDS"/>
 <u>21</u><!-- Number Of Sub-segments -->
 <v2 x="35.77062225341797" y="324.03571"/><!-- Sub-segment #0 -->
 <v2 x="35.77936553955078" y="324.06744"/>
 <v2 x="35.79242706298828" y="324.15302"/>
 <v2 x="35.80981" y="324.29236"/>
 <v2 x="35.80981" y="324.29236"/><!-- Sub-segment #1 -->
 <v2 x="35.82719421386719" y="324.43179"/>
 <v2 x="35.84095" y="324.66367"/>
 <v2 x="35.87492370605469" y="324.8721"/>
 <v2 x="35.87492370605469" y="324.8721"/><!-- Sub-segment #2 -->
 <v2 x="35.9089" y="325.08054"/>
 <v2 x="35.93274" y="325.2597"/>
 <v2 x="36.01367" y="325.543"/>
 <v2 x="36.01367" y="325.543"/><!-- Sub-segment #3 -->
 <v2 x="36.0946044921875" y="325.82629"/>
 <v2 x="36.16509" y="326.2825"/>
 <v2 x="36.36053" y="326.57187"/>
 <v2 x="36.36053" y="326.57187"/><!-- Sub-segment #4 -->
 <v2 x="36.555973052978516" y="326.86124"/>
 <v2 x="37.01263" y="326.96341"/>
 <v2 x="37.18632507324219" y="327.27921"/>
 <v2 x="37.18632507324219" y="327.27921"/><!-- Sub-segment #5 -->
 <v2 x="37.360015869140625" y="327.595"/>
 <v2 x="37.33935" y="328.04315"/>
 <v2 x="37.402687072753906" y="328.46667"/>
 <v2 x="37.402687072753906" y="328.46667"/><!-- Sub-segment #6 -->
 <v2 x="37.466026306152344" y="328.89029"/>
 <v2 x="37.44313" y="329.38513"/>
 <v2 x="37.56635284423828" y="329.82062"/>
 <v2 x="37.56635284423828" y="329.82062"/><!-- Sub-segment #7 -->
 <v2 x="37.6895751953125" y="330.2561"/>
 <v2 x="38.00986" y="330.74582"/>
 <v2 x="38.142032623291016" y="331.07968"/>
 <v2 x="38.142032623291016" y="331.07968"/><!-- Sub-segment #8 -->
 <v2 x="38.27420425415039" y="331.41354"/>
 <v2 x="38.33170700073242" y="331.56125"/>
 <v2 x="38.359375" y="331.82376"/>
 <v2 x="38.359375" y="331.82376"/><!-- Sub-segment #9 -->
 <v2 x="38.38704299926758" y="332.08633"/>
 <v2 x="38.32489" y="332.42233"/>
 <v2 x="38.30803680419922" y="332.65491"/>
 <v2 x="38.30803680419922" y="332.65491"/><!-- Sub-segment #10 -->
 <v2 x="38.29118347167969" y="332.88748"/>
 <v2 x="38.26555252075195" y="333.05811"/>
 <v2 x="38.25825500488281" y="333.21924"/>
 <v2 x="38.25825500488281" y="333.21924"/><!-- Sub-segment #11 -->
 <v2 x="38.250953674316406" y="333.38034"/>
 <v2 x="38.29392623901367" y="333.47757"/>
 <v2 x="38.26424789428711" y="333.62164"/>
 <v2 x="38.26424789428711" y="333.62164"/><!-- Sub-segment #12 -->
 <v2 x="38.23456573486328" y="333.76575"/>
 <v2 x="38.14267349243164" y="333.93283"/>
 <v2 x="38.08017" y="334.08371"/>
 <v2 x="38.08017" y="334.08371"/><!-- Sub-segment #13 -->
 <v2 x="38.01766586303711" y="334.23459"/>
 <v2 x="37.97173309326172" y="334.38754"/>
 <v2 x="37.88923" y="334.52692"/>
 <v2 x="37.88923" y="334.52692"/><!-- Sub-segment #14 -->
 <v2 x="37.806724548339844" y="334.66626"/>
 <v2 x="37.67106246948242" y="334.78104"/>
 <v2 x="37.58513259887695" y="334.91986"/>
 <v2 x="37.58513259887695" y="334.91986"/><!-- Sub-segment #15 -->
 <v2 x="37.499202728271484" y="335.05875"/>
 <v2 x="37.3923" y="335.19986"/>
 <v2 x="37.37365" y="335.36002"/>
 <v2 x="37.37365" y="335.36002"/><!-- Sub-segment #16 -->
 <v2 x="37.355" y="335.5202"/>
 <v2 x="37.471946716308594" y="335.64233"/>
 <v2 x="37.47323226928711" y="335.88092"/>
 <v2 x="37.47323226928711" y="335.88092"/><!-- Sub-segment #17 -->
 <v2 x="37.474517822265625" y="336.11954"/>
 <v2 x="37.49727" y="336.54312"/>
 <v2 x="37.38136" y="336.7916"/>
 <v2 x="37.38136" y="336.7916"/><!-- Sub-segment #18 -->
 <v2 x="37.26545" y="337.04007"/>
 <v2 x="37.024044036865234" y="337.26651"/>
 <v2 x="36.77777" y="337.3718"/>
 <v2 x="36.77777" y="337.3718"/><!-- Sub-segment #19 -->
 <v2 x="36.531494140625" y="337.47708"/>
 <v2 x="36.14221" y="337.33936"/>
 <v2 x="35.90371" y="337.42337"/>
 <v2 x="35.90371" y="337.42337"/><!-- Sub-segment #20 -->
 <v2 x="35.66521453857422" y="337.50739"/>
 <v2 x="35.47957229614258" y="337.6582"/>
 <v2 x="35.34678649902344" y="337.87582"/>
 <!-- Lengths Of Sub-segments -->
 <flt_ary>0.25999876856803894 0.5840153694152832 0.6863850951194763 1.092029333114624 1.098857045173645 1.2156234979629517 1.3671547174453735 1.3875740766525269 0.7791681885719299 0.8349260091781616 0.5671678185462952 0.40430906414985657 0.4987356662750244 0.48363906145095825 0.4979892671108246 0.4931856691837311 0.534554660320282 0.9229459762573242 0.8551563620567322 0.8834344744682312 0.7331998348236084</flt_ary>
 <!-- Cummulative Lengths Of Sub-segments -->
 <flt_ary>0.0 0.25999876856803894 0.8440141677856445 1.5303993225097656 2.6224286556243896 3.721285820007324 4.936909198760986 6.30406379699707 7.691637992858887 8.470806121826172 9.305731773376465 9.8729 10.277209281921387 10.775944709777832 11.259583473205566 11.757573127746582 12.25075912475586 12.785313606262207 13.70826 14.56341552734375 15.44685</flt_ary>
 <flt>16.18005</flt><!-- Length Of Segment -->
 <u>1000</u>
 <!-- Domestic Trade Route IDs -->
 <u4_ary/>
 <!-- International Trade Route IDs -->
 <u4_ary>650547908 650548040 655487032 651038820</u4_ary>
 <u>1293</u>
 <flt>16.18005</flt>
 <rec type="LINE_OF_SIGHT">
  <yes/>
  <v2 x="28.75" y="321.25"/>
  <v2 x="46.25" y="345.0"/>
  <xml_include path="quadtree/1294.xml"/>
 </rec>
 <i>628681992</i>
 <yes/><!-- Land -->
</rec>
