<?xml version="1.0"?>
<rec type="OBSTACLE_BASE_GRID_NODE">
 <u>7709</u>
 <u>2</u>
 <ary type="MANAGED_OBSTACLE_BOUNDARY">
  <rec type="MANAGED_OBSTACLE_BOUNDARY">
   <u>4464</u>
   <u>0</u>
   <yes/>
   <u4_ary>637655994 1</u4_ary>
  </rec>
  <rec type="MANAGED_OBSTACLE_BOUNDARY">
   <u>2322</u>
   <u>1</u>
   <yes/>
   <u4_ary>603922809 1</u4_ary>
  </rec>
  <rec type="MANAGED_OBSTACLE_BOUNDARY">
   <u>3737</u>
   <u>2</u>
   <yes/>
   <u4_ary>603922809 1 620092194 1</u4_ary>
  </rec>
  <rec type="MANAGED_OBSTACLE_BOUNDARY">
   <u>4596</u>
   <u>2</u>
   <yes/>
   <u4_ary>603922809 1 620092194 1 637655994 1</u4_ary>
  </rec>
  <rec type="MANAGED_OBSTACLE_BOUNDARY">
   <u>3725</u>
   <u>1</u>
   <yes/>
   <u4_ary>620092194 1</u4_ary>
  </rec>
  <rec type="MANAGED_OBSTACLE_BOUNDARY">
   <u>4019</u>
   <u>0</u>
   <yes/>
   <u4_ary>637655994 0</u4_ary>
  </rec>
  <rec type="MANAGED_OBSTACLE_BOUNDARY">
   <u>4106</u>
   <u>2</u>
   <yes/>
   <u4_ary>603922809 1 620092194 1 637655994 0</u4_ary>
  </rec>
 </ary>
 <ary type="MANAGED_OBSTACLE_BOUNDARY">
  <rec type="MANAGED_OBSTACLE_BOUNDARY">
   <yes/>
   <u4_ary>637655994 1</u4_ary>
  </rec>
  <rec type="MANAGED_OBSTACLE_BOUNDARY">
   <yes/>
   <u4_ary>637655994 0</u4_ary>
  </rec>
  <rec type="MANAGED_OBSTACLE_BOUNDARY">
   <yes/>
   <u4_ary>620092194 1</u4_ary>
  </rec>
  <rec type="MANAGED_OBSTACLE_BOUNDARY">
   <yes/>
   <u4_ary>603922809 1</u4_ary>
  </rec>
  <rec type="MANAGED_OBSTACLE_BOUNDARY">
   <yes/>
   <u4_ary>603922809 1 620092194 1</u4_ary>
  </rec>
  <rec type="MANAGED_OBSTACLE_BOUNDARY">
   <yes/>
   <u4_ary>603922809 1 620092194 1 637655994 0</u4_ary>
  </rec>
  <rec type="MANAGED_OBSTACLE_BOUNDARY">
   <yes/>
   <u4_ary>603922809 1 620092194 1 637655994 1</u4_ary>
  </rec>
 </ary>
</rec>
