<?xml version="1.0"?>
<rec type="INTERNATIONAL_TRADE_ROUTES">
 <s>portugal</s>
 <ary type="FACTION_INTERNATIONAL_TRADE_ROUTES_ARRAY">
  <rec type="FACTION_INTERNATIONAL_TRADE_ROUTES_ARRAY">
   <rec type="INTERNATIONAL_TRADE_ROUTE">
    <u>2</u><!-- Number Of Connections -->
    <i>606641120</i><!-- Region ID Of Home Faction -->
    <v2 x="0.0" y="0.0"/>
    <u>43</u><!-- Port OR Settlement Indice Start Point (port:portugal:porto) -->
    <u>68</u><!-- Port OR Settlement Indice End Point (port:england:bristol) -->
    <yes/><!-- Trading Over Sea -->
    <i>600997632</i><!-- Region ID Of Home Faction -->
    <v2 x="0.0" y="0.0"/>
    <u>4294967295</u>
    <u>4294967295</u>
    <no/><!-- Trading Over Sea -->
    <yes/>
    <u4_ary>20 0 33 22 0 0 0 0</u4_ary><!-- Commodities Quantity -->
    <u>1669</u>
    <u>1244</u>
    <u>0</u>
    <u>425</u>
    <u>0</u>
    <u>0</u>
    <u>0</u>
    <u4_ary>0 0 0 0 0 0 0 0 0 0 0 0 0 0 0 0 0 0 0 0</u4_ary><!-- Resources Quantity -->
    <u>0</u>
    <i>652786200</i>
   </rec>
   <u>652786200</u><!-- Route ID -->
  </rec>
  <rec type="FACTION_INTERNATIONAL_TRADE_ROUTES_ARRAY">
   <rec type="INTERNATIONAL_TRADE_ROUTE">
    <u>2</u><!-- Number Of Connections -->
    <i>606641120</i><!-- Region ID Of Home Faction -->
    <v2 x="0.0" y="0.0"/>
    <u>43</u><!-- Port OR Settlement Indice Start Point (port:portugal:porto) -->
    <u>110</u><!-- Port OR Settlement Indice End Point (port:bijapur:vengurla) -->
    <yes/><!-- Trading Over Sea -->
    <i>612203304</i><!-- Region ID Of Home Faction -->
    <v2 x="0.0" y="0.0"/>
    <u>4294967295</u>
    <u>4294967295</u>
    <no/><!-- Trading Over Sea -->
    <yes/>
    <u4_ary>17 0 27 18 0 0 0 0</u4_ary><!-- Commodities Quantity -->
    <u>1351</u>
    <u>1028</u>
    <u>0</u>
    <u>323</u>
    <u>0</u>
    <u>0</u>
    <u>0</u>
    <u4_ary>0 0 0 0 0 0 0 0 0 0 0 0 0 0 0 0 0 0 0 0</u4_ary><!-- Resources Quantity -->
    <u>0</u>
    <i>652786332</i>
   </rec>
   <u>652786332</u><!-- Route ID -->
  </rec>
  <rec type="FACTION_INTERNATIONAL_TRADE_ROUTES_ARRAY">
   <rec type="INTERNATIONAL_TRADE_ROUTE">
    <u>2</u><!-- Number Of Connections -->
    <i>606641120</i><!-- Region ID Of Home Faction -->
    <v2 x="0.0" y="0.0"/>
    <u>43</u><!-- Port OR Settlement Indice Start Point (port:portugal:porto) -->
    <u>3</u><!-- Port OR Settlement Indice End Point (port:persia:bandar_abbas) -->
    <yes/><!-- Trading Over Sea -->
    <i>600365192</i><!-- Region ID Of Home Faction -->
    <v2 x="0.0" y="0.0"/>
    <u>4294967295</u>
    <u>4294967295</u>
    <no/><!-- Trading Over Sea -->
    <yes/>
    <u4_ary>9 0 16 10 0 0 0 0</u4_ary><!-- Commodities Quantity -->
    <u>865</u>
    <u>576</u>
    <u>0</u>
    <u>289</u>
    <u>0</u>
    <u>0</u>
    <u>0</u>
    <u4_ary>0 0 0 0 0 0 0 0 0 0 0 0 0 0 0 0 0 0 0 0</u4_ary><!-- Resources Quantity -->
    <u>0</u>
    <i>652786464</i>
   </rec>
   <u>652786464</u><!-- Route ID -->
  </rec>
  <rec type="FACTION_INTERNATIONAL_TRADE_ROUTES_ARRAY">
   <rec type="INTERNATIONAL_TRADE_ROUTE">
    <u>2</u><!-- Number Of Connections -->
    <i>606641120</i><!-- Region ID Of Home Faction -->
    <v2 x="0.0" y="0.0"/>
    <u>257</u><!-- Port OR Settlement Indice Start Point (portugal) -->
    <u>149</u><!-- Port OR Settlement Indice End Point (spain) -->
    <no/><!-- Trading Over Sea -->
    <i>868012760</i><!-- Region ID Of Trading Faction -->
    <v2 x="0.0" y="0.0"/>
    <u>4294967295</u>
    <u>4294967295</u>
    <no/><!-- Trading Over Sea -->
    <no/>
    <u4_ary>8 0 14 9 0 0 0 0</u4_ary><!-- Commodities Quantity -->
    <u>920</u>
    <u>512</u>
    <u>0</u>
    <u>408</u>
    <u>0</u>
    <u>0</u>
    <u>0</u>
    <u4_ary>0 0 0 0 0 0 0 0 0 0 0 0 0 0 0 0 0 0 0 0</u4_ary><!-- Resources Quantity -->
    <u>0</u>
    <i>652786596</i>
   </rec>
   <u>652786596</u><!-- Route ID -->
  </rec>
 </ary>
</rec>
